onpremgpusdk/__init__.py
onpremgpusdk/data/__init__.py
onpremgpusdk/data/__s3util__.py
onpremgpusdk/data/datautil.py
onpremgpusdk-1.0.3.dist-info/METADATA
onpremgpusdk-1.0.3.dist-info/WHEEL
onpremgpusdk-1.0.3.dist-info/top_level.txt
onpremgpusdk-1.0.3.dist-info/RECORD
